README.rst
setup.cfg
setup.py
charlesbot_pagerduty/__init__.py
charlesbot_pagerduty/pagerduty.py
charlesbot_pagerduty/pagerduty_helpers.py
charlesbot_pagerduty/pagerduty_schedule.py
charlesbot_pagerduty/pagerduty_user.py
charlesbot_pagerduty.egg-info/PKG-INFO
charlesbot_pagerduty.egg-info/SOURCES.txt
charlesbot_pagerduty.egg-info/dependency_links.txt
charlesbot_pagerduty.egg-info/not-zip-safe
charlesbot_pagerduty.egg-info/requires.txt
charlesbot_pagerduty.egg-info/top_level.txt