Metadata-Version: 1.1
Name: charlesbot-pagerduty
Version: 1.0.1
Summary: A charlesbot pagerduty plugin
Home-page: https://github.com/marvinpinto/charlesbot-pagerduty
Author: Marvin Pinto
Author-email: marvin@pinto.im
License: MIT
Keywords: slack robot chatops charlesbot charlesbot-pagerduty
Platform: UNKNOWN
Classifier: Development Status :: 3 - Alpha
Classifier: Intended Audience :: Developers
Classifier: License :: OSI Approved :: MIT License
Classifier: Programming Language :: Python :: 3.4
